fixed_income_cl/__init__.py
fixed_income_cl/main.py
fixed_income_cl-0.0.1.2.dist-info/METADATA
fixed_income_cl-0.0.1.2.dist-info/WHEEL
fixed_income_cl-0.0.1.2.dist-info/top_level.txt
fixed_income_cl-0.0.1.2.dist-info/RECORD
