Metadata-Version: 2.4
Name: fixed_income_cl
Version: 0.0.1.2
Author: Manuel Progaska
Requires-Dist: pandas
Requires-Dist: numpy
Requires-Dist: requests
Dynamic: author
Dynamic: description
Dynamic: description-content-type
Dynamic: requires-dist
